{"codigo":39223,"razao":"VINICIUS HENRIQUE GOMES DUARTE","fantasia":"EMPORO BLUT","cnpj":"49.458.121/0001-70","cpf":null,"endereco":{"logradouro":"AVENIDA VISCONDE DE TAUNAY","complemento":"QD.J, LT.16, Nº570","fone":null,"celular":null},"bairro":{"nome":"BAIRRO JUNDIAI"},"atividades":[{"subclasse":"4723-7/00","tipo":"Principal","atividade":"Comercio varejista de bebidas","equipe":"AG","complexidade":"BAIXA"}],"alvara_ultimo":null,"inspecoes":[{"ndoc":95749,"dt_visita":"2024-01-10","tipo":"TERMO DE INTIMAÇÃO","numer":"107227","pz_retorno":0}]}