{"codigo":39697,"razao":"SOUZA E ROCHA SERVICOS MEDICOS LTDA","fantasia":"SOUZA E ROCHA SERVICOS MEDICOS","cnpj":"53.767.169/0001-38","cpf":null,"endereco":{"logradouro":"RUA  ADAMACIL VICENTE FERREIRA","complemento":"QD 49 LT 02","cep":"75-080-830"},"bairro":{"codigo":174,"nome":"RESIDENCIAL VIRGINIA CORREA"},"atividades":[],"alvara_ultimo":{"numero":20252526,"status":"","dt_emite":"2025-10-31","dt_validade":"2026-10-30"},"inspecoes":[{"controle":118166,"ndoc":115734,"dt_visita":"2025-07-01"}]}