{ "codigo":30076, "razao":"DROGARIA FAMILIAR LTDA-ME", "fantasia":"DROGARIA FAMILIAR", "inspecoes":[{"controle":104344,"ndoc":99839,"dt_visita":"2024-04-26","documento_emitido":"CERTIDÃO","numero_documento":"000000","prazo_retorno":"0","descricao_path":"his\\39\\99839.json"},{"controle":74765,"ndoc":67240,"dt_visita":"2020-08-20","documento_emitido":"TERMO DE NOTIFICAÇÃO","numero_documento":"81894","prazo_retorno":"0","descricao_path":"his\\40\\67240.json"},{"controle":74644,"ndoc":67111,"dt_visita":"2020-08-14","documento_emitido":"B","numero_documento":"81853","prazo_retorno":"0","descricao_path":"his\\11\\67111.json"},{"controle":74645,"ndoc":67112,"dt_visita":"2020-08-14","documento_emitido":"AUTO DE IMPOSIÇÃO DE PENALIDADE","numero_documento":"81854","prazo_retorno":"0","descricao_path":"his\\12\\67112.json"},{"controle":67914,"ndoc":59998,"dt_visita":"2019-08-08","documento_emitido":"TERMO DE INTIMAÇÃO","numero_documento":"74963","prazo_retorno":"0","descricao_path":"his\\98\\59998.json"}] }