{ "codigo":30165, "razao":"RBR DISTRIBUIDORA DE BEBIDAS ALTAS HORAS LTDA", "fantasia":"DISK CERVEJA ALTAS HORAS", "inspecoes":[{"controle":124050,"ndoc":122525,"dt_visita":"2025-12-03","documento_emitido":"TERMO DE INTIMAÇÃO","numero_documento":"119723","prazo_retorno":"30","descricao_path":"his\\25\\122525.json"},{"controle":87393,"ndoc":80751,"dt_visita":"2022-07-01","documento_emitido":"TERMO DE INTIMAÇÃO","numero_documento":"87436","prazo_retorno":"1","descricao_path":"his\\51\\80751.json"},{"controle":85914,"ndoc":79155,"dt_visita":"2022-05-04","documento_emitido":"TERMO DE INTIMAÇÃO","numero_documento":"92799","prazo_retorno":"0","descricao_path":"his\\55\\79155.json"}] }