{"codigo":30215,"razao":"GRACIEL SOARES DOS SANTOS","fantasia":"CIEL GAS","cnpj":"29.504.031/0001-61","cpf":null,"endereco":{"logradouro":"RUA S-82","complemento":"Quadra 22, Lote 21","fone":null,"celular":null},"bairro":{"nome":"JARDIM EUROPA"},"atividades":[{"subclasse":"4712-1/00","tipo":"Principal","atividade":"Comercio varejista de mercadorias em geral, com predominancia de produtos alimenticios - minimercados, mercearias e armazens","equipe":"AG","complexidade":"BAIXA"}],"alvara_ultimo":{"dt_validade":"2022-06-22","exercicio":2021},"inspecoes":[{"ndoc":73267,"dt_visita":"2021-07-28","tipo":"TERMO DE INTIMAÇÃO","numer":"87961","pz_retorno":0},{"ndoc":73268,"dt_visita":"2021-07-28","tipo":"AUTO DE IMPOSIÇÃO DE PENALIDADE","numer":"87962","pz_retorno":0},{"ndoc":63252,"dt_visita":"2019-12-09","tipo":"TERMO DE INTIMAÇÃO","numer":"76850","pz_retorno":15},{"ndoc":60877,"dt_visita":"2019-09-13","tipo":"PRORROGAÇÃO","numer":"98376","pz_retorno":40},{"ndoc":60117,"dt_visita":"2019-08-13","tipo":"TERMO DE INTIMAÇÃO","numer":"75250","pz_retorno":30}]}