{"codigo":22305,"razao":"ALEX BARCELOS FERNANDES","fantasia":"CENTRO MEDICO MARIA AMELIA","cnpj":null,"cpf":"762.820.821-53","endereco":{"logradouro":"AV.SENADOR JOSE LOURENÇO DIAS","complemento":"Nº 798","cep":"75-000-000"},"bairro":{"codigo":49,"nome":"CENTRO"},"atividades":[],"alvara_ultimo":{"numero":202101941,"status":"","dt_emite":"2021-10-28","dt_validade":"2022-10-27"},"inspecoes":[{"controle":81912,"ndoc":74823,"dt_visita":"2021-10-07"},{"controle":75164,"ndoc":67667,"dt_visita":"2020-09-11"},{"controle":64615,"ndoc":56454,"dt_visita":"2019-03-07"},{"controle":42447,"ndoc":33744,"dt_visita":"2013-06-24"}]}