{"codigo":26537,"razao":"060 COMERCIO DE COMBUSTIVEIS LTDA","fantasia":"AUTO POSTO CERRADO 060","cnpj":"20.681.810/0001-68","cpf":null,"endereco":{"logradouro":"ROD. BR 060","complemento":"KM 81","fone":"3324-4842","celular":"(62)98167-5828"},"bairro":{"nome":"ZONA RURAL"},"atividades":[{"subclasse":"4731-8/00","tipo":"Principal","atividade":"Comércio varejista de combustíveis para veículos automotores","equipe":"AM","complexidade":"MÉDIA"},{"subclasse":"4729-6/02","tipo":"Secundária","atividade":"Comércio varejista de mercadorias em lojas de conveniência","equipe":"AG","complexidade":"BAIXA"}],"alvara_ultimo":{"dt_validade":"2026-10-05","exercicio":2025},"inspecoes":[{"ndoc":117083,"dt_visita":"2025-08-06","tipo":"PRORROGAÇÃO","numer":"114179","pz_retorno":30},{"ndoc":115712,"dt_visita":"2025-07-02","tipo":"PRORROGAÇÃO","numer":"114179","pz_retorno":30},{"ndoc":113159,"dt_visita":"2025-05-23","tipo":"CERTIDÃO","numer":"090909","pz_retorno":0},{"ndoc":111933,"dt_visita":"2025-04-25","tipo":"PRORROGAÇÃO","numer":"114179","pz_retorno":30},{"ndoc":111720,"dt_visita":"2025-04-22","tipo":"CERTIDÃO","numer":"000000","pz_retorno":0},{"ndoc":110610,"dt_visita":"2025-03-20","tipo":"TERMO DE INTIMAÇÃO","numer":"114179","pz_retorno":10},{"ndoc":96395,"dt_visita":"2024-01-31","tipo":"CERTIDÃO","numer":null,"pz_retorno":0},{"ndoc":93757,"dt_visita":"2023-10-27","tipo":"TERMO DE NOTIFICAÇÃO","numer":"102891","pz_retorno":0},{"ndoc":93534,"dt_visita":"2023-10-20","tipo":"TERMO DE INTIMAÇÃO","numer":"102888","pz_retorno":30},{"ndoc":83184,"dt_visita":"2022-09-27","tipo":"CERTIDÃO","numer":"000000","pz_retorno":0},{"ndoc":79432,"dt_visita":"2022-05-19","tipo":"TERMO DE INTIMAÇÃO","numer":"93230","pz_retorno":0},{"ndoc":70914,"dt_visita":"2021-04-07","tipo":"TERMO DE INTIMAÇÃO","numer":"84871","pz_retorno":0},{"ndoc":70819,"dt_visita":"2021-04-05","tipo":"TERMO DE INTIMAÇÃO","numer":"84976","pz_retorno":45},{"ndoc":69512,"dt_visita":"2021-01-08","tipo":"TERMO DE INTIMAÇÃO","numer":"00000","pz_retorno":0},{"ndoc":69513,"dt_visita":"2021-01-08","tipo":"AUTO DE IMPOSIÇÃO DE PENALIDADE","numer":"00000","pz_retorno":0},{"ndoc":69514,"dt_visita":"2021-01-08","tipo":"AUTO DE IMPOSIÇÃO DE PENALIDADE","numer":"00000","pz_retorno":0},{"ndoc":69505,"dt_visita":"2021-01-08","tipo":"AUTO DE IMPOSIÇÃO DE PENALIDADE","numer":"00000","pz_retorno":0},{"ndoc":62940,"dt_visita":"2019-11-28","tipo":"TERMO DE INTIMAÇÃO","numer":"76930","pz_retorno":20},{"ndoc":60507,"dt_visita":"2019-08-22","tipo":"TERMO DE INTIMAÇÃO","numer":"75538","pz_retorno":30}]}