{"codigo":26592,"razao":"HILDA DA SILVA 563.470.811-72","fantasia":"SALAO NOVO ESTILO","cnpj":"30.509.066/0001-72","cpf":null,"endereco":{"logradouro":"RUA SD-006","complemento":"S/N QD.15 LT.1A","fone":"9301-0532","celular":null},"bairro":{"nome":"BAIRRO SANTOS DUMONT"},"atividades":[{"subclasse":"9602-5/01","tipo":"Principal","atividade":"Cabeleireiros, manicure, pedicure","equipe":"AO","complexidade":"BAIXA"},{"subclasse":"4772-5/00","tipo":"Secundária","atividade":"Comercio varejista de cosmeticos, produtos de perfumaria e de higiene pessoal","equipe":"CS","complexidade":"BAIXA"}],"alvara_ultimo":{"dt_validade":"2019-08-05","exercicio":2018},"inspecoes":[]}