{"codigo":26675,"razao":"CONSTRUTORA VALE SAO PATRICIO EIRELI-ME","fantasia":"COSNTRUTORA VALESA","cnpj":"08.960.326/0001-72","cpf":null,"endereco":{"logradouro":"RUA MANOEL D ABADIA","complemento":"SL 08 AND 01 N. 95","cep":"75-020-200"},"bairro":{"codigo":49,"nome":"CENTRO"},"atividades":[],"alvara_ultimo":{"numero":201806620,"status":"","dt_emite":"2018-12-10","dt_validade":"2019-12-09"},"inspecoes":[{"controle":110421,"ndoc":106866,"dt_visita":"2024-11-14"},{"controle":75333,"ndoc":67839,"dt_visita":"2020-09-21"},{"controle":74517,"ndoc":66980,"dt_visita":"2020-08-11"},{"controle":59728,"ndoc":51235,"dt_visita":"2018-08-13"}]}