{ "codigo":15373, "razao":"PREFEITURA MUNICIPAL DE ANAPOLIS", "fantasia":"CAPS - VIVER AD", "inspecoes":[{"controle":121944,"ndoc":120088,"dt_visita":"2025-10-03","documento_emitido":"TERMO DE INTIMAÇÃO","numero_documento":"118526","prazo_retorno":"45","descricao_path":"his\\88\\120088.json"},{"controle":121359,"ndoc":119403,"dt_visita":"2025-09-18","documento_emitido":"TERMO DE NOTIFICAÇÃO","numero_documento":"116963","prazo_retorno":"0","descricao_path":"his\\03\\119403.json"},{"controle":121049,"ndoc":119042,"dt_visita":"2025-09-12","documento_emitido":"TERMO DE NOTIFICAÇÃO","numero_documento":"116960","prazo_retorno":"0","descricao_path":"his\\42\\119042.json"},{"controle":86180,"ndoc":79445,"dt_visita":"2022-05-19","documento_emitido":"TERMO DE NOTIFICAÇÃO","numero_documento":"93106","prazo_retorno":"0","descricao_path":"his\\45\\79445.json"},{"controle":82741,"ndoc":75723,"dt_visita":"2021-12-13","documento_emitido":"TERMO DE NOTIFICAÇÃO","numero_documento":"88838","prazo_retorno":"0","descricao_path":"his\\23\\75723.json"},{"controle":79331,"ndoc":72107,"dt_visita":"2021-06-18","documento_emitido":"TERMO DE INTIMAÇÃO","numero_documento":"86039","prazo_retorno":"45","descricao_path":"his\\07\\72107.json"},{"controle":77369,"ndoc":70036,"dt_visita":"2021-02-02","documento_emitido":"TERMO DE INTIMAÇÃO","numero_documento":"83902","prazo_retorno":"30","descricao_path":"his\\36\\70036.json"},{"controle":71183,"ndoc":63438,"dt_visita":"2019-12-17","documento_emitido":"TERMO DE NOTIFICAÇÃO","numero_documento":"77906","prazo_retorno":"0","descricao_path":"his\\38\\63438.json"},{"controle":69840,"ndoc":62010,"dt_visita":"2019-10-22","documento_emitido":"TERMO DE NOTIFICAÇÃO","numero_documento":"76756","prazo_retorno":"0","descricao_path":"his\\10\\62010.json"},{"controle":67669,"ndoc":59737,"dt_visita":"2019-07-24","documento_emitido":"TERMO DE NOTIFICAÇÃO","numero_documento":"75003","prazo_retorno":"0","descricao_path":"his\\37\\59737.json"},{"controle":63349,"ndoc":55097,"dt_visita":"2019-01-11","documento_emitido":"TERMO DE INTIMAÇÃO","numero_documento":"70535","prazo_retorno":"45","descricao_path":"his\\97\\55097.json"},{"controle":63166,"ndoc":54896,"dt_visita":"2018-12-27","documento_emitido":"TERMO DE NOTIFICAÇÃO","numero_documento":"70061","prazo_retorno":"0","descricao_path":"his\\96\\54896.json"},{"controle":62510,"ndoc":54195,"dt_visita":"2018-12-04","documento_emitido":"TERMO DE NOTIFICAÇÃO","numero_documento":"69233","prazo_retorno":"0","descricao_path":"his\\95\\54195.json"},{"controle":60051,"ndoc":51543,"dt_visita":"2018-08-23","documento_emitido":"TERMO DE NOTIFICAÇÃO","numero_documento":"67201","prazo_retorno":"0","descricao_path":"his\\43\\51543.json"},{"controle":59743,"ndoc":51252,"dt_visita":"2018-08-13","documento_emitido":"TERMO DE INTIMAÇÃO","numero_documento":"66449","prazo_retorno":"30","descricao_path":"his\\52\\51252.json"},{"controle":52068,"ndoc":42982,"dt_visita":"2014-04-24","documento_emitido":"TERMO DE NOTIFICAÇÃO","numero_documento":"33713","prazo_retorno":"0","descricao_path":"his\\82\\42982.json"},{"controle":48866,"ndoc":40783,"dt_visita":"2013-12-18","documento_emitido":"RELATÓRIO TÉCNICO","numero_documento":"00000","prazo_retorno":"0","descricao_path":"his\\83\\40783.json"},{"controle":48015,"ndoc":39874,"dt_visita":"2013-11-26","documento_emitido":"TERMO DE NOTIFICAÇÃO","numero_documento":"31372","prazo_retorno":"0","descricao_path":"his\\74\\39874.json"},{"controle":46481,"ndoc":38215,"dt_visita":"2013-10-09","documento_emitido":"TERMO DE INTIMAÇÃO","numero_documento":"29671","prazo_retorno":"30","descricao_path":"his\\15\\38215.json"},{"controle":46484,"ndoc":38218,"dt_visita":"2013-10-09","documento_emitido":"CERTIDÃO","numero_documento":"00000","prazo_retorno":"0","descricao_path":"his\\18\\38218.json"},{"controle":45889,"ndoc":37566,"dt_visita":"2013-09-24","documento_emitido":"TERMO DE INTIMAÇÃO","numero_documento":"29657","prazo_retorno":"0","descricao_path":"his\\66\\37566.json"},{"controle":19576,"ndoc":8285,"dt_visita":"2011-07-11","documento_emitido":"TERMO DE INTIMAÇÃO","numero_documento":"9674","prazo_retorno":"0","descricao_path":"his\\85\\8285.json"},{"controle":19566,"ndoc":8274,"dt_visita":"2011-07-07","documento_emitido":"RELATÓRIO DE INSPEÇÃO","numero_documento":"2","prazo_retorno":"0","descricao_path":"his\\74\\8274.json"}] }