{ "codigo":32443, "razao":"CAIXETA ALIMENTACAO EIRELI", "fantasia":"CAIXETA ALIMENTACAO", "inspecoes":[{"controle":115060,"ndoc":112192,"dt_visita":"2025-04-30","documento_emitido":"CERTIDÃO","numero_documento":"000000","prazo_retorno":"0","descricao_path":"his\\92\\112192.json"},{"controle":94334,"ndoc":88536,"dt_visita":"2023-04-17","documento_emitido":"CERTIDÃO","numero_documento":"000001","prazo_retorno":"1","descricao_path":"his\\36\\88536.json"},{"controle":75590,"ndoc":68107,"dt_visita":"2020-10-06","documento_emitido":"TERMO DE INTIMAÇÃO","numero_documento":"82170","prazo_retorno":"30","descricao_path":"his\\07\\68107.json"}] }