{ "codigo":32898, "razao":"REFEICOES AO PONTO LTDA", "fantasia":"", "inspecoes":[{"controle":112608,"ndoc":109360,"dt_visita":"2025-02-12","documento_emitido":"TERMO DE INTIMAÇÃO","numero_documento":"113689","prazo_retorno":"45","descricao_path":"his\\60\\109360.json"},{"controle":111328,"ndoc":107888,"dt_visita":"2024-12-17","documento_emitido":"TERMO DE NOTIFICAÇÃO","numero_documento":"113226","prazo_retorno":"30","descricao_path":"his\\88\\107888.json"},{"controle":106217,"ndoc":102041,"dt_visita":"2024-06-21","documento_emitido":"TERMO DE NOTIFICAÇÃO","numero_documento":"109127","prazo_retorno":"0","descricao_path":"his\\41\\102041.json"},{"controle":100463,"ndoc":95385,"dt_visita":"2023-12-27","documento_emitido":"TERMO DE INTIMAÇÃO","numero_documento":"104050","prazo_retorno":"0","descricao_path":"his\\85\\95385.json"},{"controle":99998,"ndoc":94878,"dt_visita":"2023-12-08","documento_emitido":"CERTIDÃO","numero_documento":"097296","prazo_retorno":"0","descricao_path":"his\\78\\94878.json"},{"controle":99816,"ndoc":94670,"dt_visita":"2023-11-29","documento_emitido":"TERMO DE INTIMAÇÃO","numero_documento":"097296","prazo_retorno":"15","descricao_path":"his\\70\\94670.json"},{"controle":92872,"ndoc":86876,"dt_visita":"2023-02-16","documento_emitido":"TERMO DE INTIMAÇÃO","numero_documento":"097859","prazo_retorno":"45","descricao_path":"his\\76\\86876.json"},{"controle":90516,"ndoc":84224,"dt_visita":"2022-11-08","documento_emitido":"TERMO DE INTIMAÇÃO","numero_documento":"09614","prazo_retorno":"30","descricao_path":"his\\24\\84224.json"},{"controle":87886,"ndoc":81294,"dt_visita":"2022-07-21","documento_emitido":"TERMO DE INTIMAÇÃO","numero_documento":"94357","prazo_retorno":"45","descricao_path":"his\\94\\81294.json"},{"controle":81548,"ndoc":74430,"dt_visita":"2021-09-22","documento_emitido":"TERMO DE INTIMAÇÃO","numero_documento":"88367","prazo_retorno":"45","descricao_path":"his\\30\\74430.json"},{"controle":79465,"ndoc":72244,"dt_visita":"2021-06-23","documento_emitido":"TERMO DE INTIMAÇÃO","numero_documento":"86832","prazo_retorno":"45","descricao_path":"his\\44\\72244.json"}] }