{"codigo":27324,"razao":"JOAO FRANCISCO ALVES JUNIOR","fantasia":"CONSULTORIO VETERINARIO","cnpj":null,"cpf":"712.405.601-25","endereco":{"logradouro":"RUA 5","complemento":"QD. 14, LT. 31","fone":null,"celular":null},"bairro":{"nome":"SETOR INDUSTRIAL MUNIR CALIXTO"},"atividades":[{"subclasse":"7500-1/00","tipo":"Principal","atividade":"Atividades veterinarias","equipe":"VT","complexidade":"MÉDIA"}],"alvara_ultimo":{"dt_validade":"2019-10-25","exercicio":2018},"inspecoes":[{"ndoc":60064,"dt_visita":"2019-08-12","tipo":"TERMO DE INTIMAÇÃO","numer":"74534","pz_retorno":30},{"ndoc":57007,"dt_visita":"2019-03-25","tipo":"TERMO DE INTIMAÇÃO","numer":"72136","pz_retorno":5},{"ndoc":52543,"dt_visita":"2018-09-24","tipo":"TERMO DE INTIMAÇÃO","numer":"68133","pz_retorno":15}]}