{"codigo":27361,"razao":"NOVA INDUSTRIA E COMERCIO DE METAIS EIRELI","fantasia":"NOVA INDUSTRIA E COMERCIO DE METAIS","cnpj":"24.889.633/0001-60","cpf":null,"endereco":{"logradouro":"AVENIDA IPIRANGA","complemento":"QD.01, LT.01","fone":"3242-5631","celular":null},"bairro":{"nome":"JARDIM SAO PAULO"},"atividades":[{"subclasse":"3831-9/01","tipo":"Secundária","atividade":"Recuperacao de sucatas de aluminio","equipe":"AM","complexidade":"BAIXA"},{"subclasse":"4687-7/01","tipo":"Secundária","atividade":null,"equipe":null,"complexidade":null},{"subclasse":"4687-7/03","tipo":"Secundária","atividade":"Comercio atacadista de residuos e sucatas metalicos","equipe":"AM","complexidade":"BAIXA"},{"subclasse":"3839-4/99","tipo":"Secundária","atividade":"Recuperacao de materiais nao especificados anteriormente","equipe":"AM","complexidade":"BAIXA"}],"alvara_ultimo":{"dt_validade":"2020-12-02","exercicio":2019},"inspecoes":[{"ndoc":62139,"dt_visita":"2019-10-24","tipo":"TERMO DE INTIMAÇÃO","numer":"76623","pz_retorno":45},{"ndoc":54050,"dt_visita":"2018-11-28","tipo":"TERMO DE INTIMAÇÃO","numer":"69527","pz_retorno":45},{"ndoc":52995,"dt_visita":"2018-10-09","tipo":"TERMO DE INTIMAÇÃO","numer":"68711","pz_retorno":30}]}