{"codigo":34523,"razao":"MARCO AURELIO DA SILVA SOUZA","fantasia":"CASA DE CARNES MUNDAO CAIPIRA","cnpj":"37.327.042/0001-41","cpf":null,"endereco":{"logradouro":"AVENIDA DOS ESTADOS","complemento":"qd 19, lt 15","fone":null,"celular":null},"bairro":{"nome":"JARDIM DOS IPES"},"atividades":[{"subclasse":"4722-9/01","tipo":"Principal","atividade":"Comercio varejista de carnes - acougues","equipe":"AG","complexidade":"MÉDIA"}],"alvara_ultimo":null,"inspecoes":[{"ndoc":74953,"dt_visita":"2021-10-15","tipo":"TERMO DE INTIMAÇÃO","numer":"89544","pz_retorno":45}]}