{"codigo":9794,"razao":"SANDRA PAVLIKOFF ISSA MATTOS","fantasia":"MATER BABY","cnpj":null,"cpf":"373.409.051-20","endereco":{"logradouro":"AV. SANTOS DUMONT","complemento":"530","fone":null,"celular":null},"bairro":{"nome":"BAIRRO JUNDIAI"},"atividades":[{"subclasse":"8630-5/03","tipo":"Principal","atividade":"Atividade medica ambulatorial restrita a consultas","equipe":"SS","complexidade":"MÉDIA"}],"alvara_ultimo":null,"inspecoes":[{"ndoc":48490,"dt_visita":"2014-11-17","tipo":"ATO ADMINISTRATIVO DA GERÊNCIA","numer":"30301","pz_retorno":0},{"ndoc":44918,"dt_visita":"2014-07-04","tipo":"RÉPLICA FISCAL","numer":"00000","pz_retorno":0},{"ndoc":30624,"dt_visita":"2013-03-25","tipo":"CERTIDÃO","numer":"00000","pz_retorno":0},{"ndoc":28993,"dt_visita":"2013-02-18","tipo":"TERMO DE NOTIFICAÇÃO","numer":"30309","pz_retorno":0},{"ndoc":28987,"dt_visita":"2013-02-18","tipo":"TERMO DE INTIMAÇÃO","numer":"30216","pz_retorno":30},{"ndoc":15960,"dt_visita":"2012-02-27","tipo":"TERMO DE INTIMAÇÃO","numer":"15808","pz_retorno":30},{"ndoc":6592,"dt_visita":"2011-05-03","tipo":"TERMO DE INTIMAÇÃO","numer":"16178","pz_retorno":30},{"ndoc":3125,"dt_visita":"2010-05-26","tipo":"TERMO DE INTIMAÇÃO","numer":"9251","pz_retorno":30}]}