{ "codigo":9087, "razao":"BABYMANIA FRALDAS DESCARTAVEIS LTDA", "fantasia":"BABY MANIA", "inspecoes":[{"controle":70887,"ndoc":63126,"dt_visita":"2019-12-04","documento_emitido":"CERTIDÃO","numero_documento":"00001","prazo_retorno":"0","descricao_path":"his\\26\\63126.json"},{"controle":59821,"ndoc":51335,"dt_visita":"2018-08-16","documento_emitido":"TERMO DE INTIMAÇÃO","numero_documento":"67328","prazo_retorno":"30","descricao_path":"his\\35\\51335.json"},{"controle":58404,"ndoc":49770,"dt_visita":"2018-06-07","documento_emitido":"TERMO DE NOTIFICAÇÃO","numero_documento":"65665","prazo_retorno":"0","descricao_path":"his\\70\\49770.json"},{"controle":56747,"ndoc":47969,"dt_visita":"2014-11-11","documento_emitido":"TERMO DE NOTIFICAÇÃO","numero_documento":"38412","prazo_retorno":"0","descricao_path":"his\\69\\47969.json"},{"controle":56172,"ndoc":47346,"dt_visita":"2014-10-13","documento_emitido":"TERMO DE INTIMAÇÃO","numero_documento":"38185","prazo_retorno":"15","descricao_path":"his\\46\\47346.json"},{"controle":53819,"ndoc":44845,"dt_visita":"2014-07-02","documento_emitido":"TERMO DE NOTIFICAÇÃO","numero_documento":"35857","prazo_retorno":"0","descricao_path":"his\\45\\44845.json"},{"controle":53773,"ndoc":44796,"dt_visita":"2014-07-02","documento_emitido":"TERMO DE INTIMAÇÃO","numero_documento":"36027","prazo_retorno":"30","descricao_path":"his\\96\\44796.json"},{"controle":52869,"ndoc":43834,"dt_visita":"2014-05-27","documento_emitido":"PRORROGAÇÃO","numero_documento":"00001","prazo_retorno":"0","descricao_path":"his\\34\\43834.json"},{"controle":52114,"ndoc":43033,"dt_visita":"2014-04-28","documento_emitido":"TERMO DE NOTIFICAÇÃO","numero_documento":"30137","prazo_retorno":"0","descricao_path":"his\\33\\43033.json"},{"controle":41672,"ndoc":32891,"dt_visita":"2013-05-28","documento_emitido":"TERMO DE INTIMAÇÃO","numero_documento":"28073","prazo_retorno":"30","descricao_path":"his\\91\\32891.json"},{"controle":38657,"ndoc":29524,"dt_visita":"2013-02-28","documento_emitido":"PRORROGAÇÃO","numero_documento":"30036","prazo_retorno":"0","descricao_path":"his\\24\\29524.json"},{"controle":38207,"ndoc":29022,"dt_visita":"2013-02-19","documento_emitido":"TERMO DE INTIMAÇÃO","numero_documento":"30036","prazo_retorno":"10","descricao_path":"his\\22\\29022.json"},{"controle":31497,"ndoc":21476,"dt_visita":"2012-07-23","documento_emitido":"TERMO DE NOTIFICAÇÃO","numero_documento":"02239","prazo_retorno":"0","descricao_path":"his\\76\\21476.json"},{"controle":31197,"ndoc":21151,"dt_visita":"2012-07-13","documento_emitido":"TERMO DE INTIMAÇÃO","numero_documento":"01792","prazo_retorno":"5","descricao_path":"his\\51\\21151.json"},{"controle":31195,"ndoc":21149,"dt_visita":"2012-07-13","documento_emitido":"TERMO DE INTIMAÇÃO","numero_documento":"01791","prazo_retorno":"30","descricao_path":"his\\49\\21149.json"},{"controle":28874,"ndoc":18629,"dt_visita":"2012-05-09","documento_emitido":"TERMO DE INTIMAÇÃO","numero_documento":"17339","prazo_retorno":"30","descricao_path":"his\\29\\18629.json"},{"controle":28234,"ndoc":17897,"dt_visita":"2012-04-20","documento_emitido":"TERMO DE NOTIFICAÇÃO","numero_documento":"17336","prazo_retorno":"10","descricao_path":"his\\97\\17897.json"},{"controle":27854,"ndoc":17481,"dt_visita":"2012-01-30","documento_emitido":"TERMO DE INTIMAÇÃO","numero_documento":"13662","prazo_retorno":"30","descricao_path":"his\\81\\17481.json"},{"controle":25027,"ndoc":14372,"dt_visita":"2012-01-20","documento_emitido":"TERMO DE INTIMAÇÃO","numero_documento":"13666","prazo_retorno":"30","descricao_path":"his\\72\\14372.json"},{"controle":25028,"ndoc":14373,"dt_visita":"2012-01-20","documento_emitido":"TERMO DE INTIMAÇÃO","numero_documento":"13665","prazo_retorno":"30","descricao_path":"his\\73\\14373.json"},{"controle":25029,"ndoc":14374,"dt_visita":"2012-01-20","documento_emitido":"TERMO DE INTIMAÇÃO","numero_documento":"13664","prazo_retorno":"30","descricao_path":"his\\74\\14374.json"},{"controle":24970,"ndoc":14307,"dt_visita":"2012-01-18","documento_emitido":"TERMO DE NOTIFICAÇÃO","numero_documento":"13659","prazo_retorno":"0","descricao_path":"his\\07\\14307.json"},{"controle":22488,"ndoc":11512,"dt_visita":"2011-10-21","documento_emitido":"TERMO DE NOTIFICAÇÃO","numero_documento":"12165","prazo_retorno":"1","descricao_path":"his\\12\\11512.json"},{"controle":22490,"ndoc":11515,"dt_visita":"2011-10-21","documento_emitido":"TERMO DE NOTIFICAÇÃO","numero_documento":"12165","prazo_retorno":"1","descricao_path":"his\\15\\11515.json"},{"controle":22021,"ndoc":10994,"dt_visita":"2011-10-07","documento_emitido":"TERMO DE NOTIFICAÇÃO","numero_documento":"09963","prazo_retorno":"1","descricao_path":"his\\94\\10994.json"},{"controle":22022,"ndoc":10996,"dt_visita":"2011-10-07","documento_emitido":"TERMO DE NOTIFICAÇÃO","numero_documento":"09961","prazo_retorno":"1","descricao_path":"his\\96\\10996.json"},{"controle":22023,"ndoc":10997,"dt_visita":"2011-10-07","documento_emitido":"TERMO DE NOTIFICAÇÃO","numero_documento":"09964","prazo_retorno":"1","descricao_path":"his\\97\\10997.json"},{"controle":21712,"ndoc":10655,"dt_visita":"2011-09-27","documento_emitido":"TERMO DE NOTIFICAÇÃO","numero_documento":"11571","prazo_retorno":"1","descricao_path":"his\\55\\10655.json"},{"controle":21713,"ndoc":10656,"dt_visita":"2011-09-27","documento_emitido":"TERMO DE NOTIFICAÇÃO","numero_documento":"11573","prazo_retorno":"1","descricao_path":"his\\56\\10656.json"},{"controle":21714,"ndoc":10657,"dt_visita":"2011-09-27","documento_emitido":"TERMO DE INTIMAÇÃO","numero_documento":"11572","prazo_retorno":"1","descricao_path":"his\\57\\10657.json"},{"controle":10519,"ndoc":253,"dt_visita":"2010-06-08","documento_emitido":"TERMO DE INTIMAÇÃO","numero_documento":"9378","prazo_retorno":"1","descricao_path":"his\\53\\253.json"}] }