{ "codigo":9711, "razao":"CARLOS SOARES DE JESUS", "fantasia":"BAR E MERCEARIA DO BAMBU", "inspecoes":[{"controle":28124,"ndoc":17781,"dt_visita":"2012-04-17","documento_emitido":"TERMO DE INTIMAÇÃO","numero_documento":"17236","prazo_retorno":"30","descricao_path":"his\\81\\17781.json"},{"controle":21738,"ndoc":10684,"dt_visita":"2011-09-27","documento_emitido":"TERMO DE INTIMAÇÃO","numero_documento":"11763","prazo_retorno":"30","descricao_path":"his\\84\\10684.json"},{"controle":18216,"ndoc":6854,"dt_visita":"2011-05-11","documento_emitido":"TERMO DE INTIMAÇÃO","numero_documento":"16011","prazo_retorno":"30","descricao_path":"his\\54\\6854.json"}] }