{"codigo":9861,"razao":"JEANNA MACEDO COELHO","fantasia":"ISO","cnpj":null,"cpf":"704.837.521-34","endereco":{"logradouro":"RUA EVANGELINO MEIRELES-SL 04","complemento":"QD 45 LT 27","cep":"75-110-720"},"bairro":{"codigo":29,"nome":"BAIRRO JUNDIAI"},"atividades":[],"alvara_ultimo":{"numero":202501740,"status":"","dt_emite":"2025-08-07","dt_validade":"2026-08-06"},"inspecoes":[{"controle":123969,"ndoc":122437,"dt_visita":"2025-11-25"},{"controle":101923,"ndoc":96993,"dt_visita":"2024-02-16"},{"controle":101924,"ndoc":96994,"dt_visita":"2024-02-14"},{"controle":98411,"ndoc":93119,"dt_visita":"2023-10-03"},{"controle":97986,"ndoc":92642,"dt_visita":"2023-09-18"},{"controle":97877,"ndoc":92511,"dt_visita":"2023-09-15"},{"controle":89846,"ndoc":83459,"dt_visita":"2022-09-20"},{"controle":88999,"ndoc":82494,"dt_visita":"2022-08-31"},{"controle":79863,"ndoc":72663,"dt_visita":"2021-07-01"},{"controle":72589,"ndoc":64912,"dt_visita":"2020-02-21"},{"controle":67393,"ndoc":59442,"dt_visita":"2019-07-05"},{"controle":56439,"ndoc":47638,"dt_visita":"2014-10-20"},{"controle":55229,"ndoc":46337,"dt_visita":"2014-09-02"},{"controle":50517,"ndoc":42552,"dt_visita":"2014-03-06"},{"controle":48456,"ndoc":40336,"dt_visita":"2013-12-06"},{"controle":48382,"ndoc":40258,"dt_visita":"2013-12-05"},{"controle":40461,"ndoc":31554,"dt_visita":"2013-04-18"},{"controle":37761,"ndoc":28531,"dt_visita":"2013-02-07"},{"controle":36429,"ndoc":27058,"dt_visita":"2012-12-20"},{"controle":26546,"ndoc":16052,"dt_visita":"2012-03-01"},{"controle":17404,"ndoc":5990,"dt_visita":"2011-04-11"},{"controle":17170,"ndoc":5743,"dt_visita":"2011-03-30"}]}