{ "codigo":14828, "razao":"ASSOCIACAO BENEFICENTE IRMAS DORCAS", "fantasia":"CEI BETE SHALOM MADUREIRA", "inspecoes":[{"controle":117636,"ndoc":115119,"dt_visita":"2025-06-25","documento_emitido":"PRORROGAÇÃO","numero_documento":"116255","prazo_retorno":"15","descricao_path":"his\\19\\115119.json"},{"controle":117362,"ndoc":114822,"dt_visita":"2025-06-18","documento_emitido":"TERMO DE INTIMAÇÃO","numero_documento":"122855","prazo_retorno":"5","descricao_path":"his\\22\\114822.json"},{"controle":116089,"ndoc":113388,"dt_visita":"2025-05-27","documento_emitido":"TERMO DE NOTIFICAÇÃO","numero_documento":"116257","prazo_retorno":"0","descricao_path":"his\\88\\113388.json"},{"controle":116028,"ndoc":113304,"dt_visita":"2025-05-26","documento_emitido":"TERMO DE INTIMAÇÃO","numero_documento":"116255","prazo_retorno":"15","descricao_path":"his\\04\\113304.json"},{"controle":112934,"ndoc":109750,"dt_visita":"2025-02-26","documento_emitido":"TERMO DE INTIMAÇÃO","numero_documento":"113746","prazo_retorno":"30","descricao_path":"his\\50\\109750.json"},{"controle":105850,"ndoc":101627,"dt_visita":"2024-06-13","documento_emitido":"PRORROGAÇÃO","numero_documento":"107514","prazo_retorno":"0","descricao_path":"his\\27\\101627.json"},{"controle":102913,"ndoc":98110,"dt_visita":"2024-03-15","documento_emitido":"PRORROGAÇÃO","numero_documento":"107514","prazo_retorno":"45","descricao_path":"his\\10\\98110.json"},{"controle":97505,"ndoc":92071,"dt_visita":"2023-09-01","documento_emitido":"PRORROGAÇÃO","numero_documento":"100975","prazo_retorno":"0","descricao_path":"his\\71\\92071.json"},{"controle":97107,"ndoc":91633,"dt_visita":"2023-08-21","documento_emitido":"TERMO DE INTIMAÇÃO","numero_documento":"100975","prazo_retorno":"8","descricao_path":"his\\33\\91633.json"},{"controle":92612,"ndoc":86589,"dt_visita":"2023-02-07","documento_emitido":"TERMO DE INTIMAÇÃO","numero_documento":"097733","prazo_retorno":"30","descricao_path":"his\\89\\86589.json"},{"controle":13759,"ndoc":2010,"dt_visita":"2010-06-14","documento_emitido":"TERMO DE INTIMAÇÃO","numero_documento":"9036","prazo_retorno":"30","descricao_path":"his\\10\\2010.json"}] }