{"codigo":11632,"razao":"WILTON ANTONIO DAMASCENO","fantasia":"BAR DAMASCENO","cnpj":null,"cpf":"277.807.401-53","endereco":{"logradouro":"RUA MARCOS E MENDES","complemento":"QD.9, LT 13","cep":null},"bairro":{"codigo":115,"nome":"PARQUE DAS PRIMAVERAS"},"atividades":[{"cae_codigo":"11632","subclasse":"5611-2/02","classe":"5611202","tipo":"PRINCIPAL","atividade":null,"equipe":null,"complexidade":null}],"alvara_ultimo":{"numero":202302671,"status":"","dt_emite":"2023-12-19","dt_validade":"2024-12-17"},"inspecoes":[{"controle":99557,"ndoc":94387,"dt_visita":"2023-11-21"},{"controle":43548,"ndoc":34958,"dt_visita":"2013-07-16"},{"controle":42928,"ndoc":34276,"dt_visita":"2013-07-03"},{"controle":39082,"ndoc":30006,"dt_visita":"2013-03-08"},{"controle":26322,"ndoc":15810,"dt_visita":"2012-02-23"},{"controle":21311,"ndoc":10214,"dt_visita":"2011-09-12"}]}