{"codigo":11854,"razao":"MARCIA RIBEIRO NAZARIO","fantasia":"INOVE ODONTOLOGIA","cnpj":null,"cpf":"843.556.111-91","endereco":{"logradouro":"AVENIDA  DAHAS NICOLAU BITAR","complemento":"quadra 45 lote 13","cep":"75-114-640"},"bairro":{"codigo":27,"nome":"BAIRRO JK NOVA CAPITAL"},"atividades":[{"cae_codigo":"11854","subclasse":"8630-5/04","classe":"8630504","tipo":"PRINCIPAL","atividade":"Atividade odontológica","equipe":"OD","complexidade":"MÉDIA"}],"alvara_ultimo":{"numero":3041,"status":"","dt_emite":"2012-05-18","dt_validade":null},"inspecoes":[{"controle":56247,"ndoc":47432,"dt_visita":"2014-10-15"},{"controle":38775,"ndoc":29652,"dt_visita":"2013-03-04"},{"controle":34085,"ndoc":24412,"dt_visita":"2012-10-24"},{"controle":30291,"ndoc":20185,"dt_visita":"2012-06-18"},{"controle":29367,"ndoc":19163,"dt_visita":"2012-05-18"},{"controle":28452,"ndoc":18132,"dt_visita":"2012-04-26"},{"controle":26873,"ndoc":16420,"dt_visita":"2012-03-08"},{"controle":25638,"ndoc":15047,"dt_visita":"2012-02-08"},{"controle":22929,"ndoc":12032,"dt_visita":"2011-11-04"},{"controle":21589,"ndoc":10518,"dt_visita":"2011-09-21"},{"controle":8810,"ndoc":130,"dt_visita":"2011-02-16"},{"controle":16105,"ndoc":4608,"dt_visita":"2011-02-16"}]}