{"codigo":42526,"razao":"62.421.452 VALDECI CAMPOS DOURADO","fantasia":"","cnpj":"62.421.452/0001-02","cpf":null,"endereco":{"logradouro":"RUA: VN-20,","complemento":"Nº. 0, QUADRA 25;LOTE 20","fone":null,"celular":"(62)99972-2337"},"bairro":{"nome":"RESIDENCIAL VIDA NOVA"},"atividades":[{"subclasse":"4723-7/00","tipo":"Principal","atividade":"Comercio varejista de bebidas","equipe":"AG","complexidade":"BAIXA"},{"subclasse":"5611-2/02","tipo":"Secundária","atividade":null,"equipe":null,"complexidade":null}],"alvara_ultimo":{"dt_validade":"2026-09-21","exercicio":2025},"inspecoes":[]}