{ "codigo":13299, "razao":"ISMAEL FERNANDES DA SILVA", "fantasia":"ODONTOSIIM", "inspecoes":[{"controle":113460,"ndoc":110356,"dt_visita":"2025-03-13","documento_emitido":"TERMO DE INTIMAÇÃO","numero_documento":"114630","prazo_retorno":"45","descricao_path":"his\\56\\110356.json"},{"controle":113348,"ndoc":110232,"dt_visita":"2025-03-12","documento_emitido":"CERTIDÃO","numero_documento":"000000","prazo_retorno":"0","descricao_path":"his\\32\\110232.json"},{"controle":102686,"ndoc":97869,"dt_visita":"2024-03-06","documento_emitido":"TERMO DE INTIMAÇÃO","numero_documento":"107719","prazo_retorno":"0","descricao_path":"his\\69\\97869.json"},{"controle":63606,"ndoc":55374,"dt_visita":"2019-01-28","documento_emitido":"TERMO DE INTIMAÇÃO","numero_documento":"70284","prazo_retorno":"2","descricao_path":"his\\74\\55374.json"},{"controle":60393,"ndoc":51913,"dt_visita":"2018-09-10","documento_emitido":"TERMO DE INTIMAÇÃO","numero_documento":"67519","prazo_retorno":"5","descricao_path":"his\\13\\51913.json"},{"controle":56669,"ndoc":47885,"dt_visita":"2014-11-06","documento_emitido":"TERMO DE INTIMAÇÃO","numero_documento":"38596","prazo_retorno":"15","descricao_path":"his\\85\\47885.json"},{"controle":40486,"ndoc":31582,"dt_visita":"2013-04-18","documento_emitido":"TERMO DE INTIMAÇÃO","numero_documento":"25847","prazo_retorno":"30","descricao_path":"his\\82\\31582.json"},{"controle":21246,"ndoc":10144,"dt_visita":"2011-09-08","documento_emitido":"TERMO DE INTIMAÇÃO","numero_documento":"11046","prazo_retorno":"15","descricao_path":"his\\44\\10144.json"}] }