{"codigo":29580,"razao":"PAULO HENRIQUE OLIVEIRA DE DEUS-PHOD","fantasia":"ACADEMIA PH FITNESS","cnpj":"18.506.557/0001-64","cpf":null,"endereco":{"logradouro":"AV. BERNARDO SAYÃO","complemento":"420","cep":"75-064-238"},"bairro":{"codigo":221,"nome":"VILA JAIARA"},"atividades":[],"alvara_ultimo":{"numero":202500993,"status":"","dt_emite":"2025-05-28","dt_validade":"2026-05-27"},"inspecoes":[{"controle":116413,"ndoc":113745,"dt_visita":"2025-06-03"},{"controle":116128,"ndoc":113432,"dt_visita":"2025-05-28"},{"controle":115081,"ndoc":112215,"dt_visita":"2025-05-05"},{"controle":114945,"ndoc":112059,"dt_visita":"2025-04-29"},{"controle":106979,"ndoc":102918,"dt_visita":"2024-07-22"},{"controle":97950,"ndoc":92600,"dt_visita":"2023-09-20"},{"controle":85340,"ndoc":78526,"dt_visita":"2022-04-11"},{"controle":75482,"ndoc":67994,"dt_visita":"2020-09-28"},{"controle":68430,"ndoc":60542,"dt_visita":"2019-08-30"}]}