{"codigo":17076,"razao":"PATRICIA PEREIRA DA SILVA","fantasia":"CPO - CLINICA PLANETA ODONTOLOGIA","cnpj":null,"cpf":"814.650.331-49","endereco":{"logradouro":"RUA ERMETTI SIMONETTI      1ยบ ANDAR","complemento":"Nยบ 100","cep":null},"bairro":{"codigo":49,"nome":"CENTRO"},"atividades":[],"alvara_ultimo":null,"inspecoes":[{"controle":114307,"ndoc":111327,"dt_visita":"2025-04-07"},{"controle":84246,"ndoc":77349,"dt_visita":"2022-03-07"},{"controle":69683,"ndoc":61845,"dt_visita":"2019-10-10"},{"controle":47050,"ndoc":38830,"dt_visita":"2013-10-30"},{"controle":45127,"ndoc":36724,"dt_visita":"2013-09-03"},{"controle":38891,"ndoc":29791,"dt_visita":"2013-03-06"},{"controle":38697,"ndoc":29569,"dt_visita":"2013-03-01"},{"controle":30483,"ndoc":20390,"dt_visita":"2012-06-21"},{"controle":25515,"ndoc":14913,"dt_visita":"2012-02-06"},{"controle":22197,"ndoc":11191,"dt_visita":"2011-10-14"},{"controle":20318,"ndoc":9115,"dt_visita":"2011-08-05"}]}