{ "codigo":17738, "razao":"RAIMUNDO LEONARDO PINTO 33193223115", "fantasia":"PAPELARIA RAMOS", "inspecoes":[{"controle":121691,"ndoc":119793,"dt_visita":"2025-09-25","documento_emitido":"CERTIDÃO","numero_documento":"000000","prazo_retorno":"0","descricao_path":"his\\93\\119793.json"},{"controle":70129,"ndoc":62317,"dt_visita":"2019-11-06","documento_emitido":"TERMO DE INTIMAÇÃO","numero_documento":"73762","prazo_retorno":"1","descricao_path":"his\\17\\62317.json"},{"controle":36112,"ndoc":26711,"dt_visita":"2012-12-13","documento_emitido":"PRORROGAÇÃO","numero_documento":"22042","prazo_retorno":"20","descricao_path":"his\\11\\26711.json"},{"controle":35308,"ndoc":25823,"dt_visita":"2012-11-28","documento_emitido":"TERMO DE INTIMAÇÃO","numero_documento":"22042","prazo_retorno":"15","descricao_path":"his\\23\\25823.json"},{"controle":34318,"ndoc":24684,"dt_visita":"2012-10-31","documento_emitido":"TERMO DE INTIMAÇÃO","numero_documento":"21590","prazo_retorno":"15","descricao_path":"his\\84\\24684.json"},{"controle":22552,"ndoc":11589,"dt_visita":"2011-10-24","documento_emitido":"TERMO DE INTIMAÇÃO","numero_documento":"12399","prazo_retorno":"20","descricao_path":"his\\89\\11589.json"}] }