{"codigo":31530,"razao":"D. DOS SANTOS TAVARES COM. DE CARNES, BEBIDAS E AL","fantasia":"CASA DE CARNES TAVARES","cnpj":"36.590.609/0001-05","cpf":null,"endereco":{"logradouro":"AVENIDA CENTRAL,   SALA 01","complemento":"QD 21 LT 20","fone":"9222-6070","celular":"(62)98222-6070"},"bairro":{"nome":"RESIDENCIAL LEBLON"},"atividades":[{"subclasse":"4722-9/01","tipo":"Principal","atividade":"Comercio varejista de carnes - acougues","equipe":"AG","complexidade":"MÉDIA"},{"subclasse":"4712-1/00","tipo":"Secundária","atividade":"Comercio varejista de mercadorias em geral, com predominancia de produtos alimenticios - minimercados, mercearias e armazens","equipe":"AG","complexidade":"BAIXA"},{"subclasse":"4721-1/03","tipo":"Secundária","atividade":"Comercio varejista de laticinios e frios","equipe":"AG","complexidade":"MÉDIA"},{"subclasse":"4724-5/00","tipo":"Secundária","atividade":"Comercio varejista de hortifrutigranjeiros","equipe":"AG","complexidade":"BAIXA"}],"alvara_ultimo":null,"inspecoes":[{"ndoc":103809,"dt_visita":"2024-08-20","tipo":"TERMO DE INTIMAÇÃO","numer":"109724","pz_retorno":30},{"ndoc":101725,"dt_visita":"2024-06-13","tipo":"TERMO DE INTIMAÇÃO","numer":"106182","pz_retorno":30},{"ndoc":88573,"dt_visita":"2023-04-20","tipo":"TERMO DE INTIMAÇÃO","numer":"099321","pz_retorno":30},{"ndoc":87850,"dt_visita":"2023-03-21","tipo":"TERMO DE INTIMAÇÃO","numer":"098880","pz_retorno":30},{"ndoc":81030,"dt_visita":"2022-07-11","tipo":"TERMO DE INTIMAÇÃO","numer":"94087","pz_retorno":45},{"ndoc":78393,"dt_visita":"2022-04-06","tipo":"RELATÓRIO TÉCNICO","numer":"00000","pz_retorno":0},{"ndoc":78332,"dt_visita":"2022-04-04","tipo":"TERMO DE INTIMAÇÃO","numer":"92084","pz_retorno":30},{"ndoc":69643,"dt_visita":"2021-01-15","tipo":"TERMO DE INTIMAÇÃO","numer":"83972","pz_retorno":30},{"ndoc":66381,"dt_visita":"2020-06-16","tipo":"TERMO DE INTIMAÇÃO","numer":"80600","pz_retorno":30}]}