{ "codigo":31904, "razao":"C & A MODAS S.A", "fantasia":"C & A MODAS", "inspecoes":[{"controle":111282,"ndoc":107838,"dt_visita":"2024-12-17","documento_emitido":"CERTIDÃO","numero_documento":"000000","prazo_retorno":"0","descricao_path":"his\\38\\107838.json"},{"controle":111293,"ndoc":107849,"dt_visita":"2024-12-16","documento_emitido":"TERMO DE NOTIFICAÇÃO","numero_documento":"111070","prazo_retorno":"0","descricao_path":"his\\49\\107849.json"},{"controle":101290,"ndoc":96283,"dt_visita":"2024-01-30","documento_emitido":"TERMO DE NOTIFICAÇÃO","numero_documento":"107728","prazo_retorno":"0","descricao_path":"his\\83\\96283.json"},{"controle":96436,"ndoc":90885,"dt_visita":"2023-07-24","documento_emitido":"TERMO DE NOTIFICAÇÃO","numero_documento":"100510","prazo_retorno":"0","descricao_path":"his\\85\\90885.json"},{"controle":87952,"ndoc":81369,"dt_visita":"2022-07-27","documento_emitido":"TERMO DE NOTIFICAÇÃO","numero_documento":"94498","prazo_retorno":"0","descricao_path":"his\\69\\81369.json"},{"controle":79856,"ndoc":72656,"dt_visita":"2021-07-06","documento_emitido":"TERMO DE NOTIFICAÇÃO","numero_documento":"86912","prazo_retorno":"0","descricao_path":"his\\56\\72656.json"}] }