{"codigo":24730,"razao":"JOEL MENDES SANTIAGO","fantasia":"","cnpj":null,"cpf":"526.855.511-15","endereco":{"logradouro":"BR 153","complemento":"qd a lt 21","fone":null,"celular":null},"bairro":{"nome":"SETOR SANTA CLARA"},"atividades":[{"subclasse":"5611-2/01","tipo":"Principal","atividade":"Restaurantes e similares","equipe":"AG","complexidade":"MÉDIA"}],"alvara_ultimo":null,"inspecoes":[{"ndoc":47971,"dt_visita":"2014-11-11","tipo":"PRORROGAÇÃO","numer":"36056","pz_retorno":0},{"ndoc":47865,"dt_visita":"2014-11-06","tipo":"PRORROGAÇÃO","numer":"36056","pz_retorno":5},{"ndoc":47183,"dt_visita":"2014-10-06","tipo":"PRORROGAÇÃO","numer":"36056","pz_retorno":30},{"ndoc":46452,"dt_visita":"2014-09-04","tipo":"PRORROGAÇÃO","numer":"36056","pz_retorno":0},{"ndoc":45798,"dt_visita":"2014-08-13","tipo":"PRORROGAÇÃO","numer":"36056","pz_retorno":30},{"ndoc":44919,"dt_visita":"2014-07-03","tipo":"TERMO DE INTIMAÇÃO","numer":"36056","pz_retorno":30},{"ndoc":44867,"dt_visita":"2014-07-03","tipo":"TERMO DE NOTIFICAÇÃO","numer":"36055","pz_retorno":0}]}