{"codigo":24982,"razao":"FDSDSGDSFG","fantasia":"3G EXPRESS TRANSPORTES","cnpj":"13.552.751/0001-62","cpf":null,"endereco":{"logradouro":"BR 153 KM 128 Nº 1829 GALPÃO 1 E 2","complemento":"FAZENDA BARREIRO DO MEI","cep":"75-132-400"},"bairro":{"codigo":256,"nome":"ZONA RURAL"},"atividades":[],"alvara_ultimo":{"numero":20141418,"status":"","dt_emite":"2014-12-18","dt_validade":null},"inspecoes":[{"controle":57697,"ndoc":48976,"dt_visita":"2014-12-18"},{"controle":56962,"ndoc":48203,"dt_visita":"2014-11-20"},{"controle":55598,"ndoc":46739,"dt_visita":"2014-09-15"}]}