{"codigo":41245,"razao":"NUNES OPTICA E OPTOMETRIA LTDA","fantasia":"VISAO DE OURO CONSULTORIO DE OPTOMETRIA","cnpj":"50.132.629/0001-63","cpf":null,"endereco":{"logradouro":"AV MINAS GERAIS","complemento":"QUADRAE LOTE 10","fone":"9920-8489","celular":"(62) 9920-8489"},"bairro":{"nome":"BAIRRO JUNDIAI"},"atividades":[{"subclasse":"8650-0/99","tipo":"Principal","atividade":"Atividades de profissionais da area de saude nao especificadas anteriormente","equipe":"SS","complexidade":"BAIXA"},{"subclasse":"8690-9/01","tipo":"Secundária","atividade":"Atividades de praticas integrativas e complementares em saude humana","equipe":"SS","complexidade":"BAIXA"}],"alvara_ultimo":{"dt_validade":"2026-04-24","exercicio":2025},"inspecoes":[{"ndoc":113213,"dt_visita":"2025-05-23","tipo":"TERMO DE NOTIFICAÇÃO","numer":"116008","pz_retorno":0}]}