{"codigo":41493,"razao":"HOSPITAL E MATERNIDADE THEREZINHA DE JESUS","fantasia":"UPA DR ALAIR MAFRA","cnpj":"21.583.042/0032-79","cpf":null,"endereco":{"logradouro":"RUA 29 DE DEZEMBRO","complemento":"Q.10 L.1","fone":null,"celular":"(21)99999-1070"},"bairro":{"nome":"VILA ESPERANCA"},"atividades":[{"subclasse":"8610-1/01","tipo":"Principal","atividade":"Atividades de atendimento hospitalar, exceto pronto-socorro e unidades para atendimento a urgencias","equipe":"SS","complexidade":"ALTA"}],"alvara_ultimo":null,"inspecoes":[{"ndoc":120908,"dt_visita":"2025-10-22","tipo":"TERMO DE INTIMAÇÃO","numer":"118431","pz_retorno":30},{"ndoc":111204,"dt_visita":"2025-04-04","tipo":"TERMO DE NOTIFICAÇÃO","numer":"114918","pz_retorno":0}]}