{"codigo":40675,"razao":"COPAZIO CHOPP LTDA","fantasia":"COPAZIO CHOP","cnpj":"55.483.563/0001-70","cpf":null,"endereco":{"logradouro":"RUA VISCONDE DE TAUNAY","complemento":"nº245 QUADRA 34 LOTE 03","fone":"9134-0998","celular":"(62)99542-4352"},"bairro":{"nome":"BAIRRO JUNDIAI"},"atividades":[{"subclasse":"5611-2/02","tipo":"Principal","atividade":null,"equipe":null,"complexidade":null},{"subclasse":"5611-2/01","tipo":"Secundária","atividade":"Restaurantes e similares","equipe":"AG","complexidade":"MÉDIA"},{"subclasse":"5611-2/05","tipo":"Secundária","atividade":"Bares e outros estabelecimentos especializados em servir bebidas com entrenimento","equipe":"AG","complexidade":"BAIXA"}],"alvara_ultimo":{"dt_validade":"2026-12-08","exercicio":2025},"inspecoes":[{"ndoc":121943,"dt_visita":"2025-11-13","tipo":"TERMO DE INTIMAÇÃO","numer":"118962","pz_retorno":30},{"ndoc":120100,"dt_visita":"2025-10-02","tipo":"TERMO DE INTIMAÇÃO","numer":"118057","pz_retorno":15},{"ndoc":105419,"dt_visita":"2024-09-26","tipo":"TERMO DE INTIMAÇÃO","numer":"111089","pz_retorno":30}]}