{"codigo":40827,"razao":"HARMONIZE SAUDE LTDA","fantasia":"HARMONIZE CLINIC SAUDE E ESTETICA AVANCA","cnpj":"57.625.385/0001-08","cpf":null,"endereco":{"logradouro":"RUA HAGI","complemento":"QD 01 LT 07","cep":"75-000-000"},"bairro":{"codigo":173,"nome":"RESIDENCIAL VILLA BELLA"},"atividades":[],"alvara_ultimo":{"numero":20252945,"status":"","dt_emite":"2025-12-05","dt_validade":"2026-12-04"},"inspecoes":[{"controle":124088,"ndoc":122569,"dt_visita":"2025-12-05"},{"controle":114076,"ndoc":111062,"dt_visita":"2025-04-03"},{"controle":111673,"ndoc":108280,"dt_visita":"2024-12-24"}]}