{"codigo":12928,"razao":"VALDIVINA TEIXEIRA DA CRUZ","fantasia":"CARLINHOS GAS","cnpj":"10.883.518/0001-74","cpf":null,"endereco":{"logradouro":"PRAÇA GAL. OSORIO ESQ.C/ AV SAO FRANCISC","complemento":"QD 03 LT 15","fone":null,"celular":null},"bairro":{"nome":"BAIRRO DA LAPA"},"atividades":[],"alvara_ultimo":null,"inspecoes":[{"ndoc":15631,"dt_visita":"2012-02-16","tipo":"CERTIDÃO","numer":null,"pz_retorno":0},{"ndoc":2477,"dt_visita":"2009-09-08","tipo":"TERMO DE INTIMAÇÃO","numer":"2497","pz_retorno":0}]}