{ "codigo":12988, "razao":"ADRIANA BASTOS DE ALENCAR SOUSA", "fantasia":"BASTOS ALENCAR ODONTOLOGIA", "inspecoes":[{"controle":102541,"ndoc":97710,"dt_visita":"2024-03-05","documento_emitido":"TERMO DE NOTIFICAÇÃO","numero_documento":"105001","prazo_retorno":"0","descricao_path":"his\\10\\97710.json"},{"controle":85553,"ndoc":78753,"dt_visita":"2022-04-20","documento_emitido":"TERMO DE INTIMAÇÃO","numero_documento":"91550","prazo_retorno":"45","descricao_path":"his\\53\\78753.json"},{"controle":72118,"ndoc":64424,"dt_visita":"2020-02-07","documento_emitido":"TERMO DE NOTIFICAÇÃO","numero_documento":"78297","prazo_retorno":"0","descricao_path":"his\\24\\64424.json"},{"controle":64705,"ndoc":56546,"dt_visita":"2019-03-07","documento_emitido":"TERMO DE INTIMAÇÃO","numero_documento":"71671","prazo_retorno":"30","descricao_path":"his\\46\\56546.json"},{"controle":61372,"ndoc":52939,"dt_visita":"2018-10-09","documento_emitido":"TERMO DE NOTIFICAÇÃO","numero_documento":"68777","prazo_retorno":"0","descricao_path":"his\\39\\52939.json"},{"controle":55045,"ndoc":46142,"dt_visita":"2014-08-21","documento_emitido":"TERMO DE NOTIFICAÇÃO","numero_documento":"37535","prazo_retorno":"0","descricao_path":"his\\42\\46142.json"},{"controle":51067,"ndoc":43137,"dt_visita":"2014-03-20","documento_emitido":"TERMO DE INTIMAÇÃO","numero_documento":"32072","prazo_retorno":"30","descricao_path":"his\\37\\43137.json"},{"controle":51069,"ndoc":43140,"dt_visita":"2014-03-20","documento_emitido":"TERMO DE NOTIFICAÇÃO","numero_documento":"32010","prazo_retorno":"0","descricao_path":"his\\40\\43140.json"},{"controle":44384,"ndoc":35914,"dt_visita":"2013-08-13","documento_emitido":"TERMO DE INTIMAÇÃO","numero_documento":"27243","prazo_retorno":"30","descricao_path":"his\\14\\35914.json"},{"controle":37920,"ndoc":28707,"dt_visita":"2013-02-13","documento_emitido":"TERMO DE INTIMAÇÃO","numero_documento":"24912","prazo_retorno":"30","descricao_path":"his\\07\\28707.json"},{"controle":35276,"ndoc":25789,"dt_visita":"2012-11-28","documento_emitido":"TERMO DE NOTIFICAÇÃO","numero_documento":"22813","prazo_retorno":"0","descricao_path":"his\\89\\25789.json"},{"controle":27255,"ndoc":16840,"dt_visita":"2012-03-19","documento_emitido":"TERMO DE INTIMAÇÃO","numero_documento":"16705","prazo_retorno":"30","descricao_path":"his\\40\\16840.json"},{"controle":17067,"ndoc":5634,"dt_visita":"2011-03-25","documento_emitido":"TERMO DE INTIMAÇÃO","numero_documento":"14973","prazo_retorno":"30","descricao_path":"his\\34\\5634.json"}] }