{"codigo":20129,"razao":"ROSANGELA PEREIRA CARDOSO FONSECA","fantasia":"RO CABELEIREIROS","cnpj":"15.727.202/0001-07","cpf":null,"endereco":{"logradouro":"AV. DAS PANEIRAS","complemento":"Nº 455","fone":null,"celular":null},"bairro":{"nome":"VILA GOIS"},"atividades":[{"subclasse":"9602-5/01","tipo":"Principal","atividade":"Cabeleireiros, manicure, pedicure","equipe":"AO","complexidade":"BAIXA"}],"alvara_ultimo":null,"inspecoes":[{"ndoc":104828,"dt_visita":"2024-09-17","tipo":"CERTIDÃO","numer":"000000","pz_retorno":0},{"ndoc":29295,"dt_visita":"2013-02-22","tipo":"TERMO DE INTIMAÇÃO","numer":"30262","pz_retorno":30},{"ndoc":23467,"dt_visita":"2012-09-27","tipo":"TERMO DE INTIMAÇÃO","numer":"21184","pz_retorno":30}]}