{"codigo":20476,"razao":"CMV RESTAURANTE E CHOPERIA LTDA-ME","fantasia":"REST.E CHOP.TUCUNARE NA CHAPA","cnpj":"15.654.030/0001-99","cpf":null,"endereco":{"logradouro":"RUA PROF.ZENAIDE CAMPOS RORIZ","complemento":"n.1095 qd.54 lt.25","cep":"75-110-790"},"bairro":{"codigo":29,"nome":"BAIRRO JUNDIAI"},"atividades":[],"alvara_ultimo":null,"inspecoes":[{"controle":111160,"ndoc":107702,"dt_visita":"2024-12-10"},{"controle":46533,"ndoc":38274,"dt_visita":"2013-10-09"},{"controle":46532,"ndoc":38273,"dt_visita":"2013-10-09"},{"controle":41915,"ndoc":33158,"dt_visita":"2013-06-07"},{"controle":41914,"ndoc":33157,"dt_visita":"2013-06-07"},{"controle":41864,"ndoc":33098,"dt_visita":"2013-06-05"},{"controle":36162,"ndoc":26765,"dt_visita":"2012-12-13"}]}