{"codigo":20593,"razao":"WAGNER PEREIRA PIRES","fantasia":"BORRACHARIA W P","cnpj":"19.566.803/0001-36","cpf":null,"endereco":{"logradouro":"VIA VP R 01","complemento":"QD 2 B  MOD 05","cep":null},"bairro":{"codigo":63,"nome":"DISTRITO AGROINDUSTRIAL DE ANAPOLIS"},"atividades":[],"alvara_ultimo":null,"inspecoes":[{"controle":87967,"ndoc":81385,"dt_visita":"2022-07-22"},{"controle":62977,"ndoc":54694,"dt_visita":"2018-12-18"},{"controle":40262,"ndoc":31336,"dt_visita":"2013-04-12"},{"controle":33505,"ndoc":23731,"dt_visita":"2012-10-04"}]}