{"codigo":7244,"razao":"JOSE HENRIQUE DA SILVA","fantasia":"PEG PAG CONFIANCA","cnpj":"73.910.069/0001-26","cpf":null,"endereco":{"logradouro":"AV-D","complemento":"Nº 255 QD 43 LT 30  1ª ANDAR","fone":"3327-0828","celular":"(62)99132-1550"},"bairro":{"nome":"BAIRRO JK NOVA CAPITAL"},"atividades":[{"subclasse":"4712-1/00","tipo":"Principal","atividade":"Comercio varejista de mercadorias em geral, com predominancia de produtos alimenticios - minimercados, mercearias e armazens","equipe":"AG","complexidade":"BAIXA"}],"alvara_ultimo":{"dt_validade":"2023-04-10","exercicio":2022},"inspecoes":[{"ndoc":116896,"dt_visita":"2025-07-29","tipo":"TERMO DE NOTIFICAÇÃO","numer":"116739","pz_retorno":0},{"ndoc":89868,"dt_visita":"2023-06-14","tipo":"TERMO DE INTIMAÇÃO","numer":"100023","pz_retorno":0},{"ndoc":79681,"dt_visita":"2022-05-20","tipo":"TERMO DE INTIMAÇÃO","numer":"92696","pz_retorno":0},{"ndoc":64679,"dt_visita":"2020-02-14","tipo":"AUTO DE IMPOSIÇÃO DE PENALIDADE","numer":"79231","pz_retorno":0},{"ndoc":64678,"dt_visita":"2020-02-14","tipo":"TERMO DE INTIMAÇÃO","numer":"78230","pz_retorno":30},{"ndoc":56321,"dt_visita":"2019-02-26","tipo":"TERMO DE INTIMAÇÃO","numer":"71619","pz_retorno":0},{"ndoc":56323,"dt_visita":"2019-02-26","tipo":"AUTO DE IMPOSIÇÃO DE PENALIDADE","numer":"71620","pz_retorno":0},{"ndoc":56324,"dt_visita":"2019-02-26","tipo":"TERMO DE INTIMAÇÃO","numer":"71621","pz_retorno":0},{"ndoc":56325,"dt_visita":"2019-02-26","tipo":"AUTO DE IMPOSIÇÃO DE PENALIDADE","numer":"71622","pz_retorno":0},{"ndoc":56327,"dt_visita":"2019-02-26","tipo":"AUTO DE INFRAÇÃO","numer":"71623","pz_retorno":15},{"ndoc":49983,"dt_visita":"2018-06-14","tipo":"TERMO DE INTIMAÇÃO","numer":"66125","pz_retorno":30},{"ndoc":43357,"dt_visita":"2014-03-25","tipo":"TERMO DE INTIMAÇÃO","numer":"33182","pz_retorno":10},{"ndoc":25954,"dt_visita":"2012-12-04","tipo":"TERMO DE NOTIFICAÇÃO","numer":"22905","pz_retorno":0},{"ndoc":25969,"dt_visita":"2012-12-04","tipo":"TERMO DE INTIMAÇÃO","numer":"22976","pz_retorno":30},{"ndoc":20071,"dt_visita":"2012-06-14","tipo":"TERMO DE NOTIFICAÇÃO","numer":"00919","pz_retorno":0},{"ndoc":10122,"dt_visita":"2011-09-08","tipo":"TERMO DE INTIMAÇÃO","numer":"11148","pz_retorno":1},{"ndoc":8180,"dt_visita":"2011-07-08","tipo":"TERMO DE INTIMAÇÃO","numer":"9641","pz_retorno":30},{"ndoc":738,"dt_visita":"2008-09-29","tipo":"TERMO DE INTIMAÇÃO","numer":"30992","pz_retorno":8}]}