{"codigo":33282,"razao":"TOTAL MOTO PECAS E OFICINA LTDA","fantasia":"TOTAL MOTO PECAS","cnpj":"12.747.666/0001-97","cpf":null,"endereco":{"logradouro":"AV.BRASIL N.2217","complemento":"QD.F LT.11","fone":"9225-3931","celular":"(00)00000-0000"},"bairro":{"nome":"JARDIM GONCALVES"},"atividades":[{"subclasse":"4772-5/00","tipo":"Secundária","atividade":"Comercio varejista de cosmeticos, produtos de perfumaria e de higiene pessoal","equipe":"CS","complexidade":"BAIXA"},{"subclasse":"4543-9/00","tipo":"Secundária","atividade":"Manutencao e reparacao de motocicletas e motonetas","equipe":"AM","complexidade":"BAIXA"},{"subclasse":"4729-6/99","tipo":"Secundária","atividade":"Comercio varejista de produtos alimenticios em geral ou especializado em produtos alimenticios nao especificados anteriormente","equipe":"AG","complexidade":"BAIXA"}],"alvara_ultimo":{"dt_validade":"2026-05-29","exercicio":2025},"inspecoes":[]}