{"codigo":33673,"razao":"WESLEY TEIXEIRA SOUZA","fantasia":"BEZERRA GAS","cnpj":"40.821.591/0001-82","cpf":null,"endereco":{"logradouro":"R. VENERAVEL W.BORGES DE ALMEIDA S/N","complemento":"QD.16 LT..13","cep":"75-091-005"},"bairro":{"codigo":56,"nome":"CONJUNTO FILOSTRO MACHADO"},"atividades":[],"alvara_ultimo":{"numero":202301458,"status":"","dt_emite":"2023-07-18","dt_validade":"2024-07-16"},"inspecoes":[{"controle":100793,"ndoc":95741,"dt_visita":"2024-01-11"},{"controle":79672,"ndoc":72462,"dt_visita":"2021-06-23"}]}